pytask_vscode/__init__.py
pytask_vscode/_version.py
pytask_vscode/execution.py
pytask_vscode/plugin.py
pytask_vscode-0.0.2.dist-info/LICENSE
pytask_vscode-0.0.2.dist-info/METADATA
pytask_vscode-0.0.2.dist-info/WHEEL
pytask_vscode-0.0.2.dist-info/entry_points.txt
pytask_vscode-0.0.2.dist-info/top_level.txt
pytask_vscode-0.0.2.dist-info/RECORD
