Metadata-Version: 2.1
Name: pytask-vscode
Version: 0.0.2
Summary: Additional Logging for VS Code integration
Home-page: https://github.com/pytask-dev/pytask-vscode
Author: Max Jahn
Author-email: max.jahn45@gmail.com
License: MIT
Project-URL: Changelog, https://github.com/pytask-dev/pytask-vscode/blob/main/CHANGES.rst
Project-URL: Documentation, https://github.com/pytask-dev/pytask-vscode
Project-URL: Github, https://github.com/pytask-dev/pytask-vscode
Project-URL: Tracker, https://github.com/pytask-dev/pytask-vscode/issues
Platform: any
Classifier: Development Status :: 3 - Alpha
Classifier: License :: OSI Approved :: MIT License
Classifier: Operating System :: OS Independent
Classifier: Programming Language :: Python :: 3
Classifier: Programming Language :: Python :: 3 :: Only
Classifier: Programming Language :: Python :: 3.7
Classifier: Programming Language :: Python :: 3.8
Classifier: Programming Language :: Python :: 3.9
Classifier: Programming Language :: Python :: 3.10
Requires-Python: >=3.7
License-File: LICENSE
Requires-Dist: click
Requires-Dist: pytask >=0.4.2
Requires-Dist: requests
